setup.py
Alaa_Adel.egg-info/PKG-INFO
Alaa_Adel.egg-info/SOURCES.txt
Alaa_Adel.egg-info/dependency_links.txt
Alaa_Adel.egg-info/top_level.txt
Code/__init__.py