Metadata-Version: 1.1
Name: Alaa-Adel
Version: 0.1
Summary: simple Python library for dragging files 
Home-page: UNKNOWN
Author: Alaa_Adel
Author-email: UNKNOWN
License: UNKNOWN
Platform: UNKNOWN
Classifier: Programming Language :: Python :: 3
Classifier: Operating System :: OS Independent
Classifier: License :: OSI Approved :: MIT License
